maskteer/__init__.py
maskteer/handler.py
maskteer/maskteer.py
maskteer-0.1.0.dist-info/LICENSE
maskteer-0.1.0.dist-info/METADATA
maskteer-0.1.0.dist-info/WHEEL
maskteer-0.1.0.dist-info/top_level.txt
maskteer-0.1.0.dist-info/RECORD
