Metadata-Version: 2.1
Name: maskteer
Version: 0.1.0
Summary: Automatically mask sensitive information from logs or outputs for Django, Flask, and FastAPI applications.
Home-page: https://github.com/masashimorita/masketeer
Author: Masashi Morita
Author-email: masashi.morita.mm@gmail.com
Classifier: Programming Language :: Python :: 3
Classifier: License :: OSI Approved :: MIT License
Classifier: Operating System :: OS Independent
Requires-Python: >=3.7
License-File: LICENSE
Requires-Dist: pyyaml
